pynavio/__init__.py
pynavio/_code.py
pynavio/_mlflow.py
pynavio/client.py
pynavio/dependencies.py
pynavio/image.py
pynavio/model_helpers.py
pynavio/schema.py
pynavio/traits.py
pynavio/utils/__init__.py
pynavio/utils/common.py
pynavio/utils/conda.py
pynavio/utils/json_encoder.py
pynavio/utils/schemas.py
pynavio/utils/styling.py
pynavio-0.3.3.dist-info/licenses/AUTHORS.rst
pynavio-0.3.3.dist-info/licenses/LICENSE
pynavio-0.3.3.dist-info/METADATA
pynavio-0.3.3.dist-info/WHEEL
pynavio-0.3.3.dist-info/top_level.txt
pynavio-0.3.3.dist-info/RECORD
