Metadata-Version: 2.4
Name: pynavio
Version: 0.3.3
Summary: Python lib for navio
Home-page: https://github.com/craftworksgmbh/craftworks-pynavio
Author: craftworks
Author-email: dev-accounts@craftworks.at
License: MIT license
Keywords: pynavio
Classifier: Development Status :: 2 - Pre-Alpha
Classifier: Intended Audience :: Developers
Classifier: License :: OSI Approved :: MIT License
Classifier: Natural Language :: English
Classifier: Programming Language :: Python :: 3
Classifier: Programming Language :: Python :: 3.7
Classifier: Programming Language :: Python :: 3.8
Requires-Python: >=3.6
License-File: LICENSE
License-File: AUTHORS.rst
Requires-Dist: mlflow!=1.27.*,!=1.28.*,<3.0.0,>=1.20.1
Requires-Dist: Pillow<11.0.0,>=8.0.0
Requires-Dist: plotly<6.0.0,>=4.10.0
Requires-Dist: jsonschema>=3.2.0
Requires-Dist: pigar==0.10.0
Dynamic: author
Dynamic: author-email
Dynamic: classifier
Dynamic: description
Dynamic: description-content-type
Dynamic: home-page
Dynamic: keywords
Dynamic: license
Dynamic: license-file
Dynamic: requires-dist
Dynamic: requires-python
Dynamic: summary
